simsoil/__init__.py
simsoil/core.py
simsoil/transpiration.py
simsoil-0.1.0.dist-info/LICENSE
simsoil-0.1.0.dist-info/METADATA
simsoil-0.1.0.dist-info/WHEEL
simsoil-0.1.0.dist-info/top_level.txt
simsoil-0.1.0.dist-info/RECORD
