Metadata-Version: 2.1
Name: simsoil
Version: 0.1.0
Summary: Very simple, point-scale soil hydrology model
Home-page: UNKNOWN
Author: K. Arthur Endsley
Author-email: arthur.endsley@ntsg.umt.edu
License: UNKNOWN
Platform: UNKNOWN
Classifier: Programming Language :: Python :: 3
Classifier: Development Status :: 3 - Alpha
Classifier: Intended Audience :: Science/Research
Classifier: Topic :: Scientific/Engineering
Classifier: Topic :: Scientific/Engineering :: GIS
Classifier: Topic :: Scientific/Engineering :: Hydrology
Requires-Python: >=3.5
License-File: LICENSE
Requires-Dist: scipy (>=1.3)
Requires-Dist: numpy (>=1.13.3)
Requires-Dist: cached-property (>=1.5.1)
Provides-Extra: docs
Requires-Dist: pdoc3 (>=0.9.2) ; extra == 'docs'
